{
    "type": "Feature",
    "properties": {
        "althurayyaData": {
            "visual_center": "no"
        },
        "sources_english": {},
        "sources_arabic": {
            "0900AbuCabdAllahHimyari.RawdMictar.Shamela0001043-ara1.000023-000.json": {
                "title": "ابذه",
                "rate": 89,
                "status": "mb"
            }
        },
        "cornuData": {
            "coord_certainty": "certain",
            "toponym_translit_other": "Ābāḏaŧ",
            "cornu_URI": "ABADHA_537E297N_S",
            "toponym_arabic": "آباذة",
            "top_type_orig": "cite",
            "toponym_buckwalter": "Abadha",
            "toponym_arabic_other": "آباذة",
            "toponym_translit": "Ābāḏaŧ",
            "coord_lat": "29.78210",
            "toponym_search": "Abadha",
            "region_code": "Faris",
            "coord_lon": "53.73617",
            "region_spelled": "Fārs(or Fāris)",
            "top_type_hom": "towns"
        }
    },
    "geometry": {
        "type": "Point",
        "coordinates": [
            53.73617,
            29.7821
        ]
    }
}