{
    "type": "Feature",
    "properties": {
        "althurayyaData": {
            "visual_center": "no"
        },
        "sources_english": {},
        "sources_arabic": {
            "0900AbuCabdAllahHimyari.RawdMictar.Shamela0001043-ara1.000031-000.json": {
                "title": "ابيوود",
                "rate": 83,
                "status": "na"
            }
        },
        "cornuData": {
            "coord_certainty": "certain",
            "toponym_translit_other": "Abīward",
            "cornu_URI": "ABIWARD_595E372N_S",
            "toponym_arabic": "أبيورد",
            "top_type_orig": "cite",
            "toponym_buckwalter": "Abiward",
            "toponym_arabic_other": "أبيورد",
            "toponym_translit": "Abīward",
            "coord_lat": "37.27000",
            "toponym_search": "Abiward",
            "region_code": "Khurasan",
            "coord_lon": "59.59733",
            "region_spelled": "Ḫurāsān",
            "top_type_hom": "towns"
        }
    },
    "geometry": {
        "type": "Point",
        "coordinates": [
            59.59733,
            37.27
        ]
    }
}