{
    "type": "Feature",
    "properties": {
        "althurayyaData": {
            "visual_center": "no"
        },
        "sources_english": {},
        "sources_arabic": {
            "0900AbuCabdAllahHimyari.RawdMictar.Shamela0001043-ara1.001044-000.json": {
                "title": "العرج",
                "rate": 100,
                "status": "na"
            }
        },
        "cornuData": {
            "coord_certainty": "certain",
            "toponym_translit_other": "al-ʿArǧ",
            "cornu_URI": "ARJ_392E238N_O",
            "toponym_arabic": "العرج",
            "top_type_orig": "montee",
            "toponym_buckwalter": "al-Arj",
            "toponym_arabic_other": "العرج",
            "toponym_translit": "al-ʿArǧ",
            "coord_lat": "23.85851",
            "toponym_search": "al-Arj",
            "region_code": "Jazirat al-Arab",
            "coord_lon": "39.20944",
            "region_spelled": "Jazīraŧ al-ʿarab",
            "top_type_hom": "sites"
        }
    },
    "geometry": {
        "type": "Point",
        "coordinates": [
            39.20944,
            23.85851
        ]
    }
}