{
    "type": "Feature",
    "properties": {
        "althurayyaData": {
            "visual_center": "no"
        },
        "sources_english": {},
        "sources_arabic": {
            "0900AbuCabdAllahHimyari.RawdMictar.Shamela0001043-ara1.000179-000.json": {
                "title": "اونبه",
                "rate": 89,
                "status": "na"
            },
            "0900AbuCabdAllahHimyari.RawdMictar.Shamela0001043-ara1.000189-000.json": {
                "title": "اوفه",
                "rate": 100,
                "status": "na"
            },
            "0900AbuCabdAllahHimyari.RawdMictar.Shamela0001043-ara1.000022-000.json": {
                "title": "ابه",
                "rate": 86,
                "status": "na"
            }
        },
        "cornuData": {
            "coord_certainty": "certain",
            "toponym_translit_other": "Awbaŧ, Awfaŧ",
            "cornu_URI": "AWBA_631E344N_S",
            "toponym_arabic": "أوبة",
            "top_type_orig": "cite",
            "toponym_buckwalter": "Awba, Awfa",
            "toponym_arabic_other": "أوبة، أوفة",
            "toponym_translit": "Awbaŧ",
            "coord_lat": "34.40940",
            "toponym_search": "Awba, Awfa",
            "region_code": "Khurasan",
            "coord_lon": "63.16814",
            "region_spelled": "Ḫurāsān",
            "top_type_hom": "towns"
        }
    },
    "geometry": {
        "type": "Point",
        "coordinates": [
            63.16814,
            34.4094
        ]
    }
}