{
    "type": "Feature",
    "properties": {
        "althurayyaData": {
            "visual_center": "no"
        },
        "sources_english": {},
        "sources_arabic": {
            "0900AbuCabdAllahHimyari.RawdMictar.Shamela0001043-ara1.000224-000.json": {
                "title": "بدر",
                "rate": 100,
                "status": "na"
            }
        },
        "cornuData": {
            "coord_certainty": "certain",
            "toponym_translit_other": "Badr",
            "cornu_URI": "BADR_388E237N_S",
            "toponym_arabic": "بدر",
            "top_type_orig": "cite",
            "toponym_buckwalter": "Badr",
            "toponym_arabic_other": "بدر",
            "toponym_translit": "Badr",
            "coord_lat": "23.72676",
            "toponym_search": "Badr",
            "region_code": "Jazirat al-Arab",
            "coord_lon": "38.80098",
            "region_spelled": "Jazīraŧ al-ʿarab",
            "top_type_hom": "towns"
        }
    },
    "geometry": {
        "type": "Point",
        "coordinates": [
            38.80098,
            23.72676
        ]
    }
}