{
    "type": "Feature",
    "properties": {
        "althurayyaData": {
            "visual_center": "no"
        },
        "sources_english": {},
        "sources_arabic": {
            "0900AbuCabdAllahHimyari.RawdMictar.Shamela0001043-ara1.000205-000.json": {
                "title": "باجرا",
                "rate": 83,
                "status": "mb"
            },
            "0900AbuCabdAllahHimyari.RawdMictar.Shamela0001043-ara1.000206-000.json": {
                "title": "باجروان",
                "rate": 100,
                "status": "na"
            }
        },
        "cornuData": {
            "coord_certainty": "certain",
            "toponym_translit_other": "Bāǧarwān",
            "cornu_URI": "BAJARWAN_389E361N_S",
            "toponym_arabic": "باجروان",
            "top_type_orig": "cite",
            "toponym_buckwalter": "Bajarwan",
            "toponym_arabic_other": "باجروان",
            "toponym_translit": "Bāǧarwān",
            "coord_lat": "36.13571",
            "toponym_search": "Bajarwan",
            "region_code": "Aqur",
            "coord_lon": "38.98556",
            "region_spelled": "Aqūr (al-Jazīraŧ)",
            "top_type_hom": "towns"
        }
    },
    "geometry": {
        "type": "Point",
        "coordinates": [
            38.98556,
            36.13571
        ]
    }
}