{
    "type": "Feature",
    "properties": {
        "althurayyaData": {
            "visual_center": "no"
        },
        "sources_english": {},
        "sources_arabic": {
            "0900AbuCabdAllahHimyari.RawdMictar.Shamela0001043-ara1.000310-000.json": {
                "title": "البيلقان",
                "rate": 100,
                "status": "na"
            }
        },
        "cornuData": {
            "coord_certainty": "certain",
            "toponym_translit_other": "al-Baylaqān",
            "cornu_URI": "BAYLAQAN_474E398N_S",
            "toponym_arabic": "البيلقان",
            "top_type_orig": "cite",
            "toponym_buckwalter": "al-Baylaqan",
            "toponym_arabic_other": "البيلقان",
            "toponym_translit": "al-Baylaqān",
            "coord_lat": "39.86701",
            "toponym_search": "al-Baylaqan",
            "region_code": "Rihab",
            "coord_lon": "47.46081",
            "region_spelled": "al-Riḥāb (Caucasus)",
            "top_type_hom": "towns"
        }
    },
    "geometry": {
        "type": "Point",
        "coordinates": [
            47.46081,
            39.86701
        ]
    }
}