{
    "type": "Feature",
    "properties": {
        "althurayyaData": {
            "visual_center": "no"
        },
        "sources_english": {},
        "sources_arabic": {
            "0900AbuCabdAllahHimyari.RawdMictar.Shamela0001043-ara1.000261-000.json": {
                "title": "فحص البلوط",
                "rate": 100,
                "status": "na"
            },
            "0900AbuCabdAllahHimyari.RawdMictar.Shamela0001043-ara1.001128-000.json": {
                "title": "فحص البلوط",
                "rate": 100,
                "status": "na"
            }
        },
        "cornuData": {
            "coord_certainty": "certain",
            "toponym_translit_other": "Faḥṣ al-Ballūṭ",
            "cornu_URI": "FAHSBALLUT_048W386N_R",
            "toponym_arabic": "فحص البلوط",
            "top_type_orig": "district",
            "toponym_buckwalter": "Fahs al-Ballut",
            "toponym_arabic_other": "فحص البلوط",
            "toponym_translit": "Faḥṣ al-Ballūṭ",
            "coord_lat": "38.63018",
            "toponym_search": "Fahs al-Ballut",
            "region_code": "Andalus",
            "coord_lon": "-4.89554",
            "region_spelled": "al-Andalus (Spain)",
            "top_type_hom": "regions"
        }
    },
    "geometry": {
        "type": "Point",
        "coordinates": [
            -4.89554,
            38.63018
        ]
    }
}