{
    "type": "Feature",
    "properties": {
        "althurayyaData": {
            "visual_center": "no"
        },
        "sources_english": {},
        "sources_arabic": {
            "0900AbuCabdAllahHimyari.RawdMictar.Shamela0001043-ara1.001574-000.json": {
                "title": "همذان",
                "rate": 100,
                "status": "na"
            }
        },
        "cornuData": {
            "coord_certainty": "certain",
            "toponym_translit_other": "Hamaḏān",
            "cornu_URI": "HAMADHAN_485E347N_R",
            "toponym_arabic": "همذان",
            "top_type_orig": "region",
            "toponym_buckwalter": "Hamadhan",
            "toponym_arabic_other": "همذان",
            "toponym_translit": "Hamaḏān",
            "coord_lat": "34.77554",
            "toponym_search": "Hamadhan",
            "region_code": "Jibal",
            "coord_lon": "48.57908",
            "region_spelled": "al-Jibāl",
            "top_type_hom": "regions"
        }
    },
    "geometry": {
        "type": "Point",
        "coordinates": [
            48.57908,
            34.77554
        ]
    }
}