{
    "type": "Feature",
    "properties": {
        "althurayyaData": {
            "visual_center": "no"
        },
        "sources_english": {},
        "sources_arabic": {
            "0900AbuCabdAllahHimyari.RawdMictar.Shamela0001043-ara1.000455-000.json": {
                "title": "جلولاء",
                "rate": 91,
                "status": "mb"
            },
            "0900AbuCabdAllahHimyari.RawdMictar.Shamela0001043-ara1.000456-000.json": {
                "title": "جلولا",
                "rate": 100,
                "status": "na"
            }
        },
        "cornuData": {
            "coord_certainty": "certain",
            "toponym_translit_other": "Ǧalūlā",
            "cornu_URI": "JALULA_451E341N_S",
            "toponym_arabic": "جلولا",
            "top_type_orig": "cite",
            "toponym_buckwalter": "Jalula",
            "toponym_arabic_other": "جلولا",
            "toponym_translit": "Ǧalūlā",
            "coord_lat": "34.17989",
            "toponym_search": "Jalula",
            "region_code": "Iraq",
            "coord_lon": "45.11759",
            "region_spelled": "al-ʿIrāq",
            "top_type_hom": "towns"
        }
    },
    "geometry": {
        "type": "Point",
        "coordinates": [
            45.11759,
            34.17989
        ]
    }
}