{
    "type": "Feature",
    "properties": {
        "althurayyaData": {
            "visual_center": "no"
        },
        "sources_english": {},
        "sources_arabic": {
            "0900AbuCabdAllahHimyari.RawdMictar.Shamela0001043-ara1.000095-000.json": {
                "title": "الش",
                "rate": 86,
                "status": "na"
            }
        },
        "cornuData": {
            "coord_certainty": "certain",
            "toponym_translit_other": "al-Ǧašš",
            "cornu_URI": "JASHSH_354E330N_S",
            "toponym_arabic": "الجش",
            "top_type_orig": "bourgade",
            "toponym_buckwalter": "al-Jashsh",
            "toponym_arabic_other": "الجش",
            "toponym_translit": "al-Ǧašš",
            "coord_lat": "33.03094",
            "toponym_search": "al-Jashsh",
            "region_code": "Sham",
            "coord_lon": "35.45020",
            "region_spelled": "al-Šām (Greater Syria)",
            "top_type_hom": "villages"
        }
    },
    "geometry": {
        "type": "Point",
        "coordinates": [
            35.4502,
            33.03094
        ]
    }
}