{
    "type": "Feature",
    "properties": {
        "althurayyaData": {
            "visual_center": "no"
        },
        "sources_english": {},
        "sources_arabic": {
            "0900AbuCabdAllahHimyari.RawdMictar.Shamela0001043-ara1.000547-000.json": {
                "title": "الخانوقه",
                "rate": 100,
                "status": "na"
            }
        },
        "cornuData": {
            "coord_certainty": "certain",
            "toponym_translit_other": "al-Ḫānūqaŧ",
            "cornu_URI": "KHANUQA_398E357N_S",
            "toponym_arabic": "الخانوقة",
            "top_type_orig": "cite",
            "toponym_buckwalter": "al-Khanuqa",
            "toponym_arabic_other": "الخانوقة",
            "toponym_translit": "al-Ḫānūqaŧ",
            "coord_lat": "35.75218",
            "toponym_search": "al-Khanuqa",
            "region_code": "Aqur",
            "coord_lon": "39.81661",
            "region_spelled": "Aqūr (al-Jazīraŧ)",
            "top_type_hom": "towns"
        }
    },
    "geometry": {
        "type": "Point",
        "coordinates": [
            39.81661,
            35.75218
        ]
    }
}