{
    "type": "Feature",
    "properties": {
        "althurayyaData": {
            "visual_center": "no"
        },
        "sources_english": {},
        "sources_arabic": {
            "0900AbuCabdAllahHimyari.RawdMictar.Shamela0001043-ara1.000570-000.json": {
                "title": "خناصره",
                "rate": 86,
                "status": "na"
            },
            "0900AbuCabdAllahHimyari.RawdMictar.Shamela0001043-ara1.001512-000.json": {
                "title": "الناصره",
                "rate": 93,
                "status": "na"
            }
        },
        "cornuData": {
            "coord_certainty": "certain",
            "toponym_translit_other": "al-Ḫunāṣiraŧ",
            "cornu_URI": "KHUNASIRA_375E357N_S",
            "toponym_arabic": "الخناصرة",
            "top_type_orig": "cite",
            "toponym_buckwalter": "al-Khunasira",
            "toponym_arabic_other": "الخناصرة",
            "toponym_translit": "al-Ḫunāṣiraŧ",
            "coord_lat": "35.78031",
            "toponym_search": "al-Khunasira",
            "region_code": "Sham",
            "coord_lon": "37.50551",
            "region_spelled": "al-Šām (Greater Syria)",
            "top_type_hom": "towns"
        }
    },
    "geometry": {
        "type": "Point",
        "coordinates": [
            37.50551,
            35.78031
        ]
    }
}