{
    "type": "Feature",
    "properties": {
        "althurayyaData": {
            "visual_center": "no"
        },
        "sources_english": {},
        "sources_arabic": {
            "0900AbuCabdAllahHimyari.RawdMictar.Shamela0001043-ara1.001326-000.json": {
                "title": "لارده",
                "rate": 100,
                "status": "na"
            }
        },
        "cornuData": {
            "coord_certainty": "certain",
            "toponym_translit_other": "Lāridaŧ",
            "cornu_URI": "LARIDA_006E416N_S",
            "toponym_arabic": "لاردة",
            "top_type_orig": "placefrontiere",
            "toponym_buckwalter": "Larida",
            "toponym_arabic_other": "لاردة",
            "toponym_translit": "Lāridaŧ",
            "coord_lat": "41.60948",
            "toponym_search": "Larida",
            "region_code": "Andalus",
            "coord_lon": "0.64889",
            "region_spelled": "al-Andalus (Spain)",
            "top_type_hom": "waystations"
        }
    },
    "geometry": {
        "type": "Point",
        "coordinates": [
            0.64889,
            41.60948
        ]
    }
}