{
    "type": "Feature",
    "properties": {
        "althurayyaData": {
            "visual_center": "no"
        },
        "sources_english": {},
        "sources_arabic": {
            "0900AbuCabdAllahHimyari.RawdMictar.Shamela0001043-ara1.001471-000.json": {
                "title": "مقور",
                "rate": 86,
                "status": "na"
            }
        },
        "cornuData": {
            "coord_certainty": "certain",
            "toponym_translit_other": "Mawr",
            "cornu_URI": "MAWR_428E157N_S",
            "toponym_arabic": "مور",
            "top_type_orig": "cite",
            "toponym_buckwalter": "Mawr",
            "toponym_arabic_other": "مور",
            "toponym_translit": "Mawr",
            "coord_lat": "15.73119",
            "toponym_search": "Mawr",
            "region_code": "Yemen",
            "coord_lon": "42.89942",
            "region_spelled": "al-Yaman",
            "top_type_hom": "towns"
        }
    },
    "geometry": {
        "type": "Point",
        "coordinates": [
            42.89942,
            15.73119
        ]
    }
}