{
    "type": "Feature",
    "properties": {
        "althurayyaData": {
            "visual_center": "no"
        },
        "sources_english": {},
        "sources_arabic": {
            "0900AbuCabdAllahHimyari.RawdMictar.Shamela0001043-ara1.001168-000.json": {
                "title": "قامهل",
                "rate": 100,
                "status": "na"
            }
        },
        "cornuData": {
            "coord_certainty": "certain",
            "toponym_translit_other": "Qāmuhul",
            "cornu_URI": "QAMUHUL_717E236N_S",
            "toponym_arabic": "قامهل",
            "top_type_orig": "cite",
            "toponym_buckwalter": "Qamuhul",
            "toponym_arabic_other": "قامهل",
            "toponym_translit": "Qāmuhul",
            "coord_lat": "23.61826",
            "toponym_search": "Qamuhul",
            "region_code": "Sind",
            "coord_lon": "71.72209",
            "region_spelled": "al-Sind",
            "top_type_hom": "towns"
        }
    },
    "geometry": {
        "type": "Point",
        "coordinates": [
            71.72209,
            23.61826
        ]
    }
}