{
    "type": "Feature",
    "properties": {
        "althurayyaData": {
            "visual_center": "no"
        },
        "sources_english": {},
        "sources_arabic": {
            "0900AbuCabdAllahHimyari.RawdMictar.Shamela0001043-ara1.001228-000.json": {
                "title": "القنطره",
                "rate": 100,
                "status": "na"
            },
            "0900AbuCabdAllahHimyari.RawdMictar.Shamela0001043-ara1.001198-000.json": {
                "title": "القطريه",
                "rate": 86,
                "status": "mb"
            }
        },
        "cornuData": {
            "coord_certainty": "certain",
            "toponym_translit_other": "al-Qanṭaraŧ",
            "cornu_URI": "QANTARA_323E308N_S",
            "toponym_arabic": "القنطرة",
            "top_type_orig": "localite",
            "toponym_buckwalter": "al-Qantara",
            "toponym_arabic_other": "القنطرة",
            "toponym_translit": "al-Qanṭaraŧ",
            "coord_lat": "30.85902",
            "toponym_search": "al-Qantara",
            "region_code": "Egypt",
            "coord_lon": "32.32461",
            "region_spelled": "Miṣr (Egypt)",
            "top_type_hom": "villages"
        }
    },
    "geometry": {
        "type": "Point",
        "coordinates": [
            32.32461,
            30.85902
        ]
    }
}