{
    "type": "Feature",
    "properties": {
        "althurayyaData": {
            "visual_center": "no"
        },
        "sources_english": {},
        "sources_arabic": {
            "0900AbuCabdAllahHimyari.RawdMictar.Shamela0001043-ara1.001167-000.json": {
                "title": "قاشان",
                "rate": 100,
                "status": "na"
            }
        },
        "cornuData": {
            "coord_certainty": "certain",
            "toponym_translit_other": "Qāšān",
            "cornu_URI": "QASHAN_515E339N_R",
            "toponym_arabic": "قاشان",
            "top_type_orig": "territoire",
            "toponym_buckwalter": "Qashan",
            "toponym_arabic_other": "قاشان",
            "toponym_translit": "Qāšān",
            "coord_lat": "33.96762",
            "toponym_search": "Qashan",
            "region_code": "Jibal",
            "coord_lon": "51.50468",
            "region_spelled": "al-Jibāl",
            "top_type_hom": "regions"
        }
    },
    "geometry": {
        "type": "Point",
        "coordinates": [
            51.50468,
            33.96762
        ]
    }
}