{
    "type": "Feature",
    "properties": {
        "althurayyaData": {
            "visual_center": "no"
        },
        "sources_english": {},
        "sources_arabic": {
            "0900AbuCabdAllahHimyari.RawdMictar.Shamela0001043-ara1.001197-000.json": {
                "title": "القطيف",
                "rate": 92,
                "status": "na"
            },
            "0900AbuCabdAllahHimyari.RawdMictar.Shamela0001043-ara1.001199-000.json": {
                "title": "القطيعه",
                "rate": 86,
                "status": "na"
            },
            "0900AbuCabdAllahHimyari.RawdMictar.Shamela0001043-ara1.001198-000.json": {
                "title": "القطريه",
                "rate": 86,
                "status": "na"
            }
        },
        "cornuData": {
            "coord_certainty": "certain",
            "toponym_translit_other": "al-Quṭayyifaŧ",
            "cornu_URI": "QUTAYYIFA_366E337N_S",
            "toponym_arabic": "القطيفة",
            "top_type_orig": "etape",
            "toponym_buckwalter": "al-Qutayyifa",
            "toponym_arabic_other": "القطيفة",
            "toponym_translit": "al-Quṭayyifaŧ",
            "coord_lat": "33.74546",
            "toponym_search": "al-Qutayyifa",
            "region_code": "Sham",
            "coord_lon": "36.60247",
            "region_spelled": "al-Šām (Greater Syria)",
            "top_type_hom": "waystations"
        }
    },
    "geometry": {
        "type": "Point",
        "coordinates": [
            36.60247,
            33.74546
        ]
    }
}