{
    "type": "Feature",
    "properties": {
        "althurayyaData": {
            "visual_center": "no"
        },
        "sources_english": {},
        "sources_arabic": {
            "0900AbuCabdAllahHimyari.RawdMictar.Shamela0001043-ara1.000697-000.json": {
                "title": "الرقه",
                "rate": 83,
                "status": "mb"
            },
            "0900AbuCabdAllahHimyari.RawdMictar.Shamela0001043-ara1.000669-000.json": {
                "title": "الرافقه",
                "rate": 100,
                "status": "na"
            }
        },
        "cornuData": {
            "coord_certainty": "certain",
            "toponym_translit_other": "al-Rāfiqaŧ",
            "cornu_URI": "RAFIQA_307E306N_S",
            "toponym_arabic": "الرافقة",
            "top_type_orig": "localite",
            "toponym_buckwalter": "al-Rafiqa",
            "toponym_arabic_other": "الرافقة",
            "toponym_translit": "al-Rāfiqaŧ",
            "coord_lat": "30.69470",
            "toponym_search": "al-Rafiqa",
            "region_code": "Egypt",
            "coord_lon": "30.73593",
            "region_spelled": "Miṣr (Egypt)",
            "top_type_hom": "villages"
        }
    },
    "geometry": {
        "type": "Point",
        "coordinates": [
            30.73593,
            30.6947
        ]
    }
}