{
    "type": "Feature",
    "properties": {
        "althurayyaData": {
            "visual_center": "no"
        },
        "sources_english": {},
        "sources_arabic": {
            "0900AbuCabdAllahHimyari.RawdMictar.Shamela0001043-ara1.000774-000.json": {
                "title": "سبا",
                "rate": 86,
                "status": "na"
            }
        },
        "cornuData": {
            "coord_certainty": "certain",
            "toponym_translit_other": "Sabāʾ",
            "cornu_URI": "SABA_453E154N_R",
            "toponym_arabic": "سباء",
            "top_type_orig": "region",
            "toponym_buckwalter": "Saba",
            "toponym_arabic_other": "سباء",
            "toponym_translit": "Sabāʾ",
            "coord_lat": "15.40854",
            "toponym_search": "Saba",
            "region_code": "Yemen",
            "coord_lon": "45.33616",
            "region_spelled": "al-Yaman",
            "top_type_hom": "regions"
        }
    },
    "geometry": {
        "type": "Point",
        "coordinates": [
            45.33616,
            15.40854
        ]
    }
}