{
    "type": "Feature",
    "properties": {
        "althurayyaData": {
            "visual_center": "no"
        },
        "sources_english": {},
        "sources_arabic": {
            "0900AbuCabdAllahHimyari.RawdMictar.Shamela0001043-ara1.000787-000.json": {
                "title": "السراه",
                "rate": 83,
                "status": "na"
            }
        },
        "cornuData": {
            "coord_certainty": "certain",
            "toponym_translit_other": "al-Sidraŧ",
            "cornu_URI": "SIDRA_662E368N_S",
            "toponym_arabic": "السدرة",
            "top_type_orig": "etape",
            "toponym_buckwalter": "al-Sidra",
            "toponym_arabic_other": "السدرة",
            "toponym_translit": "al-Sidraŧ",
            "coord_lat": "36.83770",
            "toponym_search": "al-Sidra",
            "region_code": "Khurasan",
            "coord_lon": "66.21231",
            "region_spelled": "Ḫurāsān",
            "top_type_hom": "waystations"
        }
    },
    "geometry": {
        "type": "Point",
        "coordinates": [
            66.21231,
            36.8377
        ]
    }
}