{
    "type": "Feature",
    "properties": {
        "althurayyaData": {
            "visual_center": "no"
        },
        "sources_english": {},
        "sources_arabic": {
            "0900AbuCabdAllahHimyari.RawdMictar.Shamela0001043-ara1.000912-000.json": {
                "title": "صحار",
                "rate": 100,
                "status": "na"
            }
        },
        "cornuData": {
            "coord_certainty": "certain",
            "toponym_translit_other": "Ṣuḥār",
            "cornu_URI": "SUHAR_566E243N_S",
            "toponym_arabic": "صحار",
            "top_type_orig": "capitale",
            "toponym_buckwalter": "Suhar",
            "toponym_arabic_other": "صحار",
            "toponym_translit": "Ṣuḥār",
            "coord_lat": "24.35205",
            "toponym_search": "Suhar",
            "region_code": "Jazirat al-Arab",
            "coord_lon": "56.69086",
            "region_spelled": "Jazīraŧ al-ʿarab",
            "top_type_hom": "capitals"
        }
    },
    "geometry": {
        "type": "Point",
        "coordinates": [
            56.69086,
            24.35205
        ]
    }
}