{
    "type": "Feature",
    "properties": {
        "althurayyaData": {
            "visual_center": "no"
        },
        "sources_english": {},
        "sources_arabic": {
            "0900AbuCabdAllahHimyari.RawdMictar.Shamela0001043-ara1.000387-000.json": {
                "title": "توزر",
                "rate": 100,
                "status": "na"
            }
        },
        "cornuData": {
            "coord_certainty": "certain",
            "toponym_translit_other": "Tawzir",
            "cornu_URI": "TAWZIR_081E339N_S",
            "toponym_arabic": "توزر",
            "top_type_orig": "cite",
            "toponym_buckwalter": "Tawzir",
            "toponym_arabic_other": "توزر",
            "toponym_translit": "Tawzir",
            "coord_lat": "33.93695",
            "toponym_search": "Tawzir",
            "region_code": "Maghrib",
            "coord_lon": "8.15027",
            "region_spelled": "al-Maġrib",
            "top_type_hom": "towns"
        }
    },
    "geometry": {
        "type": "Point",
        "coordinates": [
            8.15027,
            33.93695
        ]
    }
}