{
    "type": "Feature",
    "properties": {
        "althurayyaData": {
            "visual_center": "no"
        },
        "sources_english": {},
        "sources_arabic": {
            "0900AbuCabdAllahHimyari.RawdMictar.Shamela0001043-ara1.000385-000.json": {
                "title": "تونس",
                "rate": 100,
                "status": "na"
            },
            "0900AbuCabdAllahHimyari.RawdMictar.Shamela0001043-ara1.000373-000.json": {
                "title": "تنس",
                "rate": 86,
                "status": "na"
            }
        },
        "cornuData": {
            "coord_certainty": "certain",
            "toponym_translit_other": "Tūnis",
            "cornu_URI": "TUNIS_101E367N_S",
            "toponym_arabic": "تونس",
            "top_type_orig": "cite",
            "toponym_buckwalter": "Tunis",
            "toponym_arabic_other": "تونس",
            "toponym_translit": "Tūnis",
            "coord_lat": "36.77071",
            "toponym_search": "Tunis",
            "region_code": "Maghrib",
            "coord_lon": "10.17736",
            "region_spelled": "al-Maġrib",
            "top_type_hom": "towns"
        }
    },
    "geometry": {
        "type": "Point",
        "coordinates": [
            10.17736,
            36.77071
        ]
    }
}