{
    "type": "Feature",
    "properties": {
        "althurayyaData": {
            "visual_center": "no"
        },
        "sources_english": {},
        "sources_arabic": {
            "0900AbuCabdAllahHimyari.RawdMictar.Shamela0001043-ara1.001603-000.json": {
                "title": "وادي درعه",
                "rate": 100,
                "status": "na"
            }
        },
        "cornuData": {
            "coord_certainty": "certain",
            "toponym_translit_other": "Wādī Darʿaŧ",
            "cornu_URI": "WADIDARA_080W291N_W",
            "toponym_arabic": "وادي درعة",
            "top_type_orig": "wadi",
            "toponym_buckwalter": "Wadi Dara",
            "toponym_arabic_other": "وادي درعة",
            "toponym_translit": "Wādī Darʿaŧ",
            "coord_lat": "29.19903",
            "toponym_search": "Wadi Dara",
            "region_code": "Maghrib",
            "coord_lon": "-8.07804",
            "region_spelled": "al-Maġrib",
            "top_type_hom": "waters"
        }
    },
    "geometry": {
        "type": "Point",
        "coordinates": [
            -8.07804,
            29.19903
        ]
    }
}